{"flowContents":{"identifier":"d682712a-2367-33bd-b53c-f1ee51525edb","instanceIdentifier":"00fc10fa-0197-1000-b22d-b1999ac42b28","name":"RAG_Query","comments":"","position":{"x":3664.0,"y":-336.0},"processGroups":[],"remoteProcessGroups":[],"processors":[{"identifier":"59c9c597-0bf8-35a6-b697-b0a729ba9fce","instanceIdentifier":"e8a8f5ef-0196-1000-0c75-16df5dadc5c2","name":"InvokeHTTP","comments":"","position":{"x":4280.0,"y":-80.0},"type":"org.apache.nifi.processors.standard.InvokeHTTP","bundle":{"group":"org.apache.nifi","artifact":"nifi-standard-nar","version":"2.4.0"},"properties":{"Request Content-Encoding":"DISABLED","proxy-configuration-service":null,"Request Multipart Form-Data Filename Enabled":"true","Request Chunked Transfer-Encoding Enabled":"false","Response Header Request Attributes Prefix":null,"HTTP/2 Disabled":"False","Connection Timeout":"60 secs","Response Cookie Strategy":"DISABLED","Socket Read Timeout":"60 secs","Socket Idle Connections":"5","Request Body Enabled":"true","OAuth2 Access Token Refresh Strategy":"ON_TOKEN_EXPIRATION","HTTP URL":"http://localhost:8017/query","Request OAuth2 Access Token Provider":null,"Socket Idle Timeout":"5 mins","Response Redirects Enabled":"True","Socket Write Timeout":"60 secs","Request Header Attributes Pattern":null,"Response FlowFile Naming Strategy":"RANDOM","Response Cache Enabled":"false","Request Date Header Enabled":"True","Request Failure Penalization Enabled":"false","Response Body Attribute Size":"256","SSL Context Service":null,"Response Generation Required":"false","Request User-Agent":null,"Response Header Request Attributes Enabled":"false","HTTP Method":"POST","Request Username":null,"Request Content-Type":"application/json","Response Body Attribute Name":null,"Request Digest Authentication Enabled":"false","Request Multipart Form-Data Name":null,"Response Cache Size":"10MB","Response Body Ignored":"false"},"propertyDescriptors":{"Request Content-Encoding":{"name":"Request Content-Encoding","displayName":"Request Content-Encoding","identifiesControllerService":false,"sensitive":false,"dynamic":false},"proxy-configuration-service":{"name":"proxy-configuration-service","displayName":"Proxy Configuration Service","identifiesControllerService":true,"sensitive":false,"dynamic":false},"Request Multipart Form-Data Filename Enabled":{"name":"Request Multipart Form-Data Filename Enabled","displayName":"Request Multipart Form-Data Filename Enabled","identifiesControllerService":false,"sensitive":false,"dynamic":false},"Request Chunked Transfer-Encoding Enabled":{"name":"Request Chunked Transfer-Encoding Enabled","displayName":"Request Chunked Transfer-Encoding Enabled","identifiesControllerService":false,"sensitive":false,"dynamic":false},"Response Header Request Attributes Prefix":{"name":"Response Header Request Attributes Prefix","displayName":"Response Header Request Attributes Prefix","identifiesControllerService":false,"sensitive":false,"dynamic":false},"HTTP/2 Disabled":{"name":"HTTP/2 Disabled","displayName":"HTTP/2 Disabled","identifiesControllerService":false,"sensitive":false,"dynamic":false},"Connection Timeout":{"name":"Connection Timeout","displayName":"Connection Timeout","identifiesControllerService":false,"sensitive":false,"dynamic":false},"Response Cookie Strategy":{"name":"Response Cookie Strategy","displayName":"Response Cookie Strategy","identifiesControllerService":false,"sensitive":false,"dynamic":false},"Request Password":{"name":"Request Password","displayName":"Request Password","identifiesControllerService":false,"sensitive":true,"dynamic":false},"Socket Read Timeout":{"name":"Socket Read Timeout","displayName":"Socket Read Timeout","identifiesControllerService":false,"sensitive":false,"dynamic":false},"Socket Idle Connections":{"name":"Socket Idle Connections","displayName":"Socket Idle Connections","identifiesControllerService":false,"sensitive":false,"dynamic":false},"Request Body Enabled":{"name":"Request Body Enabled","displayName":"Request Body Enabled","identifiesControllerService":false,"sensitive":false,"dynamic":false},"OAuth2 Access Token Refresh Strategy":{"name":"OAuth2 Access Token Refresh Strategy","displayName":"OAuth2 Access Token Refresh Strategy","identifiesControllerService":false,"sensitive":false,"dynamic":false},"HTTP URL":{"name":"HTTP URL","displayName":"HTTP URL","identifiesControllerService":false,"sensitive":false,"dynamic":false},"Request OAuth2 Access Token Provider":{"name":"Request OAuth2 Access Token Provider","displayName":"Request OAuth2 Access Token Provider","identifiesControllerService":true,"sensitive":false,"dynamic":false},"Socket Idle Timeout":{"name":"Socket Idle Timeout","displayName":"Socket Idle Timeout","identifiesControllerService":false,"sensitive":false,"dynamic":false},"Response Redirects Enabled":{"name":"Response Redirects Enabled","displayName":"Response Redirects Enabled","identifiesControllerService":false,"sensitive":false,"dynamic":false},"Socket Write Timeout":{"name":"Socket Write Timeout","displayName":"Socket Write Timeout","identifiesControllerService":false,"sensitive":false,"dynamic":false},"Request Header Attributes Pattern":{"name":"Request Header Attributes Pattern","displayName":"Request Header Attributes Pattern","identifiesControllerService":false,"sensitive":false,"dynamic":false},"Response FlowFile Naming Strategy":{"name":"Response FlowFile Naming Strategy","displayName":"Response FlowFile Naming Strategy","identifiesControllerService":false,"sensitive":false,"dynamic":false},"Response Cache Enabled":{"name":"Response Cache Enabled","displayName":"Response Cache Enabled","identifiesControllerService":false,"sensitive":false,"dynamic":false},"Request Date Header Enabled":{"name":"Request Date Header Enabled","displayName":"Request Date Header Enabled","identifiesControllerService":false,"sensitive":false,"dynamic":false},"Request Failure Penalization Enabled":{"name":"Request Failure Penalization Enabled","displayName":"Request Failure Penalization Enabled","identifiesControllerService":false,"sensitive":false,"dynamic":false},"Response Body Attribute Size":{"name":"Response Body Attribute Size","displayName":"Response Body Attribute Size","identifiesControllerService":false,"sensitive":false,"dynamic":false},"SSL Context Service":{"name":"SSL Context Service","displayName":"SSL Context Service","identifiesControllerService":true,"sensitive":false,"dynamic":false},"Response Generation Required":{"name":"Response Generation Required","displayName":"Response Generation Required","identifiesControllerService":false,"sensitive":false,"dynamic":false},"Request User-Agent":{"name":"Request User-Agent","displayName":"Request User-Agent","identifiesControllerService":false,"sensitive":false,"dynamic":false},"Response Header Request Attributes Enabled":{"name":"Response Header Request Attributes Enabled","displayName":"Response Header Request Attributes Enabled","identifiesControllerService":false,"sensitive":false,"dynamic":false},"HTTP Method":{"name":"HTTP Method","displayName":"HTTP Method","identifiesControllerService":false,"sensitive":false,"dynamic":false},"Request Username":{"name":"Request Username","displayName":"Request Username","identifiesControllerService":false,"sensitive":false,"dynamic":false},"Request Content-Type":{"name":"Request Content-Type","displayName":"Request Content-Type","identifiesControllerService":false,"sensitive":false,"dynamic":false},"Response Body Attribute Name":{"name":"Response Body Attribute Name","displayName":"Response Body Attribute Name","identifiesControllerService":false,"sensitive":false,"dynamic":false},"Request Digest Authentication Enabled":{"name":"Request Digest Authentication Enabled","displayName":"Request Digest Authentication Enabled","identifiesControllerService":false,"sensitive":false,"dynamic":false},"Request Multipart Form-Data Name":{"name":"Request Multipart Form-Data Name","displayName":"Request Multipart Form-Data Name","identifiesControllerService":false,"sensitive":false,"dynamic":false},"Response Cache Size":{"name":"Response Cache Size","displayName":"Response Cache Size","identifiesControllerService":false,"sensitive":false,"dynamic":false},"Response Body Ignored":{"name":"Response Body Ignored","displayName":"Response Body Ignored","identifiesControllerService":false,"sensitive":false,"dynamic":false}},"style":{},"schedulingPeriod":"0 sec","schedulingStrategy":"TIMER_DRIVEN","executionNode":"ALL","penaltyDuration":"30 sec","yieldDuration":"1 sec","bulletinLevel":"WARN","runDurationMillis":0,"concurrentlySchedulableTaskCount":1,"autoTerminatedRelationships":["No Retry","Retry","Original","Failure"],"scheduledState":"ENABLED","retryCount":10,"retriedRelationships":[],"backoffMechanism":"PENALIZE_FLOWFILE","maxBackoffPeriod":"10 mins","componentType":"PROCESSOR","groupIdentifier":"d682712a-2367-33bd-b53c-f1ee51525edb"},{"identifier":"6f017afd-008c-3256-8f5e-454c43cb1de0","instanceIdentifier":"ed3a6300-0196-1000-116c-d62ec7c0f6a7","name":"EvaluateJsonPath","comments":"","position":{"x":4344.0,"y":-264.0},"type":"org.apache.nifi.processors.standard.EvaluateJsonPath","bundle":{"group":"org.apache.nifi","artifact":"nifi-standard-nar","version":"2.4.0"},"properties":{"Destination":"flowfile-attribute","Max String Length":"20 MB","Return Type":"auto-detect","query":"$.query","n_results":"$.n_results","Null Value Representation":"empty string","Path Not Found Behavior":"warn"},"propertyDescriptors":{"Destination":{"name":"Destination","displayName":"Destination","identifiesControllerService":false,"sensitive":false,"dynamic":false},"Max String Length":{"name":"Max String Length","displayName":"Max String Length","identifiesControllerService":false,"sensitive":false,"dynamic":false},"Return Type":{"name":"Return Type","displayName":"Return Type","identifiesControllerService":false,"sensitive":false,"dynamic":false},"query":{"name":"query","displayName":"query","identifiesControllerService":false,"sensitive":false,"dynamic":true},"n_results":{"name":"n_results","displayName":"n_results","identifiesControllerService":false,"sensitive":false,"dynamic":true},"Null Value Representation":{"name":"Null Value Representation","displayName":"Null Value Representation","identifiesControllerService":false,"sensitive":false,"dynamic":false},"Path Not Found Behavior":{"name":"Path Not Found Behavior","displayName":"Path Not Found Behavior","identifiesControllerService":false,"sensitive":false,"dynamic":false}},"style":{},"schedulingPeriod":"0 sec","schedulingStrategy":"TIMER_DRIVEN","executionNode":"ALL","penaltyDuration":"30 sec","yieldDuration":"1 sec","bulletinLevel":"WARN","runDurationMillis":0,"concurrentlySchedulableTaskCount":1,"autoTerminatedRelationships":["failure","unmatched"],"scheduledState":"ENABLED","retryCount":10,"retriedRelationships":[],"backoffMechanism":"PENALIZE_FLOWFILE","maxBackoffPeriod":"10 mins","componentType":"PROCESSOR","groupIdentifier":"d682712a-2367-33bd-b53c-f1ee51525edb"},{"identifier":"3fa35d33-5049-3b24-b76b-1c71fe2116fb","instanceIdentifier":"f46b6660-0196-1000-aba6-638df7c2c851","name":"HandleHttpRequest","comments":"","position":{"x":4480.0,"y":-448.0},"type":"org.apache.nifi.processors.standard.HandleHttpRequest","bundle":{"group":"org.apache.nifi","artifact":"nifi-standard-nar","version":"2.4.0"},"properties":{"multipart-request-max-size":"1 MB","parameters-to-attributes":null,"Allow POST":"true","Hostname":null,"Default URL Character Set":"UTF-8","Allow DELETE":"true","Request Header Maximum Size":"8 KB","Maximum Threads":"200","HTTP Protocols":"HTTP_1_1","Additional HTTP Methods":null,"container-queue-size":"50","HTTP Context Map":"1efa7eb1-7db3-3c65-8537-d1d08aa3877f","multipart-read-buffer-size":"512 KB","SSL Context Service":null,"Allow OPTIONS":"false","Allowed Paths":null,"Allow GET":"true","Allow HEAD":"false","Listening Port":"8090","Client Authentication":"No Authentication","Allow PUT":"true"},"propertyDescriptors":{"multipart-request-max-size":{"name":"multipart-request-max-size","displayName":"Multipart Request Max Size","identifiesControllerService":false,"sensitive":false,"dynamic":false},"parameters-to-attributes":{"name":"parameters-to-attributes","displayName":"Parameters to Attributes List","identifiesControllerService":false,"sensitive":false,"dynamic":false},"Allow POST":{"name":"Allow POST","displayName":"Allow POST","identifiesControllerService":false,"sensitive":false,"dynamic":false},"Hostname":{"name":"Hostname","displayName":"Hostname","identifiesControllerService":false,"sensitive":false,"dynamic":false},"Default URL Character Set":{"name":"Default URL Character Set","displayName":"Default URL Character Set","identifiesControllerService":false,"sensitive":false,"dynamic":false},"Allow DELETE":{"name":"Allow DELETE","displayName":"Allow DELETE","identifiesControllerService":false,"sensitive":false,"dynamic":false},"Request Header Maximum Size":{"name":"Request Header Maximum Size","displayName":"Request Header Maximum Size","identifiesControllerService":false,"sensitive":false,"dynamic":false},"Maximum Threads":{"name":"Maximum Threads","displayName":"Maximum Threads","identifiesControllerService":false,"sensitive":false,"dynamic":false},"HTTP Protocols":{"name":"HTTP Protocols","displayName":"HTTP Protocols","identifiesControllerService":false,"sensitive":false,"dynamic":false},"Additional HTTP Methods":{"name":"Additional HTTP Methods","displayName":"Additional HTTP Methods","identifiesControllerService":false,"sensitive":false,"dynamic":false},"container-queue-size":{"name":"container-queue-size","displayName":"Container Queue Size","identifiesControllerService":false,"sensitive":false,"dynamic":false},"HTTP Context Map":{"name":"HTTP Context Map","displayName":"HTTP Context Map","identifiesControllerService":true,"sensitive":false,"dynamic":false},"multipart-read-buffer-size":{"name":"multipart-read-buffer-size","displayName":"Multipart Read Buffer Size","identifiesControllerService":false,"sensitive":false,"dynamic":false},"SSL Context Service":{"name":"SSL Context Service","displayName":"SSL Context Service","identifiesControllerService":true,"sensitive":false,"dynamic":false},"Allow OPTIONS":{"name":"Allow OPTIONS","displayName":"Allow OPTIONS","identifiesControllerService":false,"sensitive":false,"dynamic":false},"Allowed Paths":{"name":"Allowed Paths","displayName":"Allowed Paths","identifiesControllerService":false,"sensitive":false,"dynamic":false},"Allow GET":{"name":"Allow GET","displayName":"Allow GET","identifiesControllerService":false,"sensitive":false,"dynamic":false},"Allow HEAD":{"name":"Allow HEAD","displayName":"Allow HEAD","identifiesControllerService":false,"sensitive":false,"dynamic":false},"Listening Port":{"name":"Listening Port","displayName":"Listening Port","identifiesControllerService":false,"sensitive":false,"dynamic":false},"Client Authentication":{"name":"Client Authentication","displayName":"Client Authentication","identifiesControllerService":false,"sensitive":false,"dynamic":false},"Allow PUT":{"name":"Allow PUT","displayName":"Allow PUT","identifiesControllerService":false,"sensitive":false,"dynamic":false}},"style":{},"schedulingPeriod":"0 sec","schedulingStrategy":"TIMER_DRIVEN","executionNode":"ALL","penaltyDuration":"30 sec","yieldDuration":"1 sec","bulletinLevel":"WARN","runDurationMillis":0,"concurrentlySchedulableTaskCount":1,"autoTerminatedRelationships":[],"scheduledState":"ENABLED","retryCount":10,"retriedRelationships":[],"backoffMechanism":"PENALIZE_FLOWFILE","maxBackoffPeriod":"10 mins","componentType":"PROCESSOR","groupIdentifier":"d682712a-2367-33bd-b53c-f1ee51525edb"},{"identifier":"060ac957-b5f7-3a3e-840e-92e820792be9","instanceIdentifier":"f4353f6e-0196-1000-3875-876dce42b2e4","name":"HandleHttpResponse","comments":"","position":{"x":4864.0,"y":-232.0},"type":"org.apache.nifi.processors.standard.HandleHttpResponse","bundle":{"group":"org.apache.nifi","artifact":"nifi-standard-nar","version":"2.4.0"},"properties":{"HTTP Context Map":"1efa7eb1-7db3-3c65-8537-d1d08aa3877f","Attributes to add to the HTTP Response (Regex)":".*","HTTP Status Code":"200"},"propertyDescriptors":{"HTTP Context Map":{"name":"HTTP Context Map","displayName":"HTTP Context Map","identifiesControllerService":true,"sensitive":false,"dynamic":false},"Attributes to add to the HTTP Response (Regex)":{"name":"Attributes to add to the HTTP Response (Regex)","displayName":"Attributes to add to the HTTP Response (Regex)","identifiesControllerService":false,"sensitive":false,"dynamic":false},"HTTP Status Code":{"name":"HTTP Status Code","displayName":"HTTP Status Code","identifiesControllerService":false,"sensitive":false,"dynamic":false}},"style":{},"schedulingPeriod":"0 sec","schedulingStrategy":"TIMER_DRIVEN","executionNode":"ALL","penaltyDuration":"30 sec","yieldDuration":"1 sec","bulletinLevel":"WARN","runDurationMillis":0,"concurrentlySchedulableTaskCount":1,"autoTerminatedRelationships":["success","failure"],"scheduledState":"ENABLED","retryCount":10,"retriedRelationships":[],"backoffMechanism":"PENALIZE_FLOWFILE","maxBackoffPeriod":"10 mins","componentType":"PROCESSOR","groupIdentifier":"d682712a-2367-33bd-b53c-f1ee51525edb"},{"identifier":"e24ed96d-28a0-3ab1-90fd-3eeac45a48ea","instanceIdentifier":"f3a330b6-0196-1000-db99-3a99b583ce92","name":"ReplaceText","comments":"","position":{"x":4664.0,"y":88.0},"type":"org.apache.nifi.processors.standard.ReplaceText","bundle":{"group":"org.apache.nifi","artifact":"nifi-standard-nar","version":"2.4.0"},"properties":{"Regular Expression":"(?s)(^.*$)","Replacement Value":"{\n  \"answer\": ${answer},\n  \"sources\": ${sources}\n}\n\n","Evaluation Mode":"Entire text","Text to Prepend":null,"Line-by-Line Evaluation Mode":"All","Character Set":"UTF-8","Maximum Buffer Size":"1 MB","Replacement Strategy":"Always Replace","Text to Append":null},"propertyDescriptors":{"Regular Expression":{"name":"Regular Expression","displayName":"Search Value","identifiesControllerService":false,"sensitive":false,"dynamic":false},"Replacement Value":{"name":"Replacement Value","displayName":"Replacement Value","identifiesControllerService":false,"sensitive":false,"dynamic":false},"Evaluation Mode":{"name":"Evaluation Mode","displayName":"Evaluation Mode","identifiesControllerService":false,"sensitive":false,"dynamic":false},"Text to Prepend":{"name":"Text to Prepend","displayName":"Text to Prepend","identifiesControllerService":false,"sensitive":false,"dynamic":false},"Line-by-Line Evaluation Mode":{"name":"Line-by-Line Evaluation Mode","displayName":"Line-by-Line Evaluation Mode","identifiesControllerService":false,"sensitive":false,"dynamic":false},"Character Set":{"name":"Character Set","displayName":"Character Set","identifiesControllerService":false,"sensitive":false,"dynamic":false},"Maximum Buffer Size":{"name":"Maximum Buffer Size","displayName":"Maximum Buffer Size","identifiesControllerService":false,"sensitive":false,"dynamic":false},"Replacement Strategy":{"name":"Replacement Strategy","displayName":"Replacement Strategy","identifiesControllerService":false,"sensitive":false,"dynamic":false},"Text to Append":{"name":"Text to Append","displayName":"Text to Append","identifiesControllerService":false,"sensitive":false,"dynamic":false}},"style":{},"schedulingPeriod":"0 sec","schedulingStrategy":"TIMER_DRIVEN","executionNode":"ALL","penaltyDuration":"30 sec","yieldDuration":"1 sec","bulletinLevel":"WARN","runDurationMillis":25,"concurrentlySchedulableTaskCount":1,"autoTerminatedRelationships":["failure"],"scheduledState":"ENABLED","retryCount":10,"retriedRelationships":[],"backoffMechanism":"PENALIZE_FLOWFILE","maxBackoffPeriod":"10 mins","componentType":"PROCESSOR","groupIdentifier":"d682712a-2367-33bd-b53c-f1ee51525edb"}],"inputPorts":[],"outputPorts":[],"connections":[{"identifier":"83529543-4d55-39da-b07f-19022062f74d","instanceIdentifier":"f4734c21-0196-1000-b5d8-2accac87b7cf","name":"","source":{"id":"e24ed96d-28a0-3ab1-90fd-3eeac45a48ea","type":"PROCESSOR","groupId":"d682712a-2367-33bd-b53c-f1ee51525edb","name":"ReplaceText","comments":"","instanceIdentifier":"f3a330b6-0196-1000-db99-3a99b583ce92"},"destination":{"id":"060ac957-b5f7-3a3e-840e-92e820792be9","type":"PROCESSOR","groupId":"d682712a-2367-33bd-b53c-f1ee51525edb","name":"HandleHttpResponse","comments":"","instanceIdentifier":"f4353f6e-0196-1000-3875-876dce42b2e4"},"labelIndex":0,"zIndex":52,"selectedRelationships":["success"],"backPressureObjectThreshold":10000,"backPressureDataSizeThreshold":"1 GB","flowFileExpiration":"0 sec","prioritizers":[],"bends":[],"loadBalanceStrategy":"DO_NOT_LOAD_BALANCE","partitioningAttribute":"","loadBalanceCompression":"DO_NOT_COMPRESS","componentType":"CONNECTION","groupIdentifier":"d682712a-2367-33bd-b53c-f1ee51525edb"},{"identifier":"c5802cd3-6b3a-3e06-9a13-023fa64868ff","instanceIdentifier":"f4709726-0196-1000-a22b-ac98a7d0beda","name":"","source":{"id":"59c9c597-0bf8-35a6-b697-b0a729ba9fce","type":"PROCESSOR","groupId":"d682712a-2367-33bd-b53c-f1ee51525edb","name":"InvokeHTTP","comments":"","instanceIdentifier":"e8a8f5ef-0196-1000-0c75-16df5dadc5c2"},"destination":{"id":"e24ed96d-28a0-3ab1-90fd-3eeac45a48ea","type":"PROCESSOR","groupId":"d682712a-2367-33bd-b53c-f1ee51525edb","name":"ReplaceText","comments":"","instanceIdentifier":"f3a330b6-0196-1000-db99-3a99b583ce92"},"labelIndex":0,"zIndex":51,"selectedRelationships":["Response"],"backPressureObjectThreshold":10000,"backPressureDataSizeThreshold":"1 GB","flowFileExpiration":"0 sec","prioritizers":[],"bends":[],"loadBalanceStrategy":"DO_NOT_LOAD_BALANCE","partitioningAttribute":"","loadBalanceCompression":"DO_NOT_COMPRESS","componentType":"CONNECTION","groupIdentifier":"d682712a-2367-33bd-b53c-f1ee51525edb"},{"identifier":"010be016-2958-3538-b606-0a2cb165f75c","instanceIdentifier":"f473b533-0196-1000-9890-602d03c395e8","name":"","source":{"id":"3fa35d33-5049-3b24-b76b-1c71fe2116fb","type":"PROCESSOR","groupId":"d682712a-2367-33bd-b53c-f1ee51525edb","name":"HandleHttpRequest","comments":"","instanceIdentifier":"f46b6660-0196-1000-aba6-638df7c2c851"},"destination":{"id":"6f017afd-008c-3256-8f5e-454c43cb1de0","type":"PROCESSOR","groupId":"d682712a-2367-33bd-b53c-f1ee51525edb","name":"EvaluateJsonPath","comments":"","instanceIdentifier":"ed3a6300-0196-1000-116c-d62ec7c0f6a7"},"labelIndex":0,"zIndex":53,"selectedRelationships":["success"],"backPressureObjectThreshold":10000,"backPressureDataSizeThreshold":"1 GB","flowFileExpiration":"0 sec","prioritizers":[],"bends":[],"loadBalanceStrategy":"DO_NOT_LOAD_BALANCE","partitioningAttribute":"","loadBalanceCompression":"DO_NOT_COMPRESS","componentType":"CONNECTION","groupIdentifier":"d682712a-2367-33bd-b53c-f1ee51525edb"},{"identifier":"535ba42b-1c75-35bf-9a55-a999a4eb64ab","instanceIdentifier":"f3aef087-0196-1000-b092-4c4c242ad180","name":"","source":{"id":"6f017afd-008c-3256-8f5e-454c43cb1de0","type":"PROCESSOR","groupId":"d682712a-2367-33bd-b53c-f1ee51525edb","name":"EvaluateJsonPath","comments":"","instanceIdentifier":"ed3a6300-0196-1000-116c-d62ec7c0f6a7"},"destination":{"id":"59c9c597-0bf8-35a6-b697-b0a729ba9fce","type":"PROCESSOR","groupId":"d682712a-2367-33bd-b53c-f1ee51525edb","name":"InvokeHTTP","comments":"","instanceIdentifier":"e8a8f5ef-0196-1000-0c75-16df5dadc5c2"},"labelIndex":0,"zIndex":49,"selectedRelationships":["matched"],"backPressureObjectThreshold":10000,"backPressureDataSizeThreshold":"1 GB","flowFileExpiration":"0 sec","prioritizers":[],"bends":[],"loadBalanceStrategy":"DO_NOT_LOAD_BALANCE","partitioningAttribute":"","loadBalanceCompression":"DO_NOT_COMPRESS","componentType":"CONNECTION","groupIdentifier":"d682712a-2367-33bd-b53c-f1ee51525edb"}],"labels":[],"funnels":[],"controllerServices":[],"defaultFlowFileExpiration":"0 sec","defaultBackPressureObjectThreshold":10000,"defaultBackPressureDataSizeThreshold":"1 GB","scheduledState":"ENABLED","executionEngine":"INHERITED","maxConcurrentTasks":1,"statelessFlowTimeout":"1 min","flowFileConcurrency":"UNBOUNDED","flowFileOutboundPolicy":"STREAM_WHEN_AVAILABLE","componentType":"PROCESS_GROUP"},"externalControllerServices":{"1efa7eb1-7db3-3c65-8537-d1d08aa3877f":{"identifier":"1efa7eb1-7db3-3c65-8537-d1d08aa3877f","name":"StandardHttpContextMap"}},"parameterContexts":{},"flowEncodingVersion":"1.0","parameterProviders":{},"latest":false}